{
  "stainType": "DualStain",
  "stainId": "k67smqntttvmlna",
  "orderComment": null,
  "isBillable": true,
  "hasGCode": true,
  "isDualOrder": true,
  "hasCptCodeLevels": true,
  "testId": "KI67MA",
  "stainName": "Ki-67, Semi-quantitative/Melan A",
  "active": false,
  "stainResultGroupId": 0,
  "aliquotType": null,
  "needsAcknowledgement": true,
  "useWetProtocol": false,
  "performedByHand": false,
  "defaultResult": null,
  "requestForAdditionalReport": false,
  "histologyDisplayString": "Ki67Mel",
  "stainerType": "BenchMark ULTRA",
  "ventanaBenchMarkId": "5afdaef8584d5631244b3c5c",
  "ventanaBenchMarkWetId": null,
  "ventanaBenchMarkProtocolName": "D Ki-67.MART1",
  "hasWetProtocol": false,
  "firstTest": {
    "stainType": "GradedStain",
    "stainId": "k67smqntttve",
    "orderComment": null,
    "isBillable": true,
    "hasGCode": false,
    "isDualOrder": false,
    "hasCptCodeLevels": false,
    "testId": "116",
    "stainName": "Ki-67, Semi-quantitative",
    "active": true,
    "stainResultGroupId": 0,
    "aliquotType": null,
    "needsAcknowledgement": true,
    "useWetProtocol": false,
    "performedByHand": false,
    "defaultResult": null,
    "requestForAdditionalReport": false,
    "histologyDisplayString": "Ki-67 Semi",
    "stainerType": "BenchMark ULTRA",
    "ventanaBenchMarkId": "5afdaef8584d5631244b3c5c",
    "ventanaBenchMarkWetId": null,
    "ventanaBenchMarkProtocolName": "D Ki-67.MART1",
    "hasWetProtocol": false
  },
  "secondTest": {
    "stainType": "IHC",
    "stainId": "mlna",
    "orderComment": null,
    "isBillable": true,
    "hasGCode": true,
    "isDualOrder": false,
    "hasCptCodeLevels": true,
    "testId": "119",
    "stainName": "Melan A",
    "active": true,
    "stainResultGroupId": 0,
    "aliquotType": null,
    "needsAcknowledgement": true,
    "useWetProtocol": false,
    "performedByHand": false,
    "defaultResult": null,
    "requestForAdditionalReport": false,
    "histologyDisplayString": "Melan A",
    "stainerType": "BenchMark ULTRA",
    "ventanaBenchMarkId": "5afdaef8584d5631244b3c5c",
    "ventanaBenchMarkWetId": "5afdaef8584d5631244b3ca4",
    "ventanaBenchMarkProtocolName": "D Ki-67.MART1",
    "hasWetProtocol": true
  },
  "depricatedFirstTestId": "225",
  "depricatedSecondTestId": null
}